main.py
toyserve-0.0.0.dist-info/METADATA
toyserve-0.0.0.dist-info/WHEEL
toyserve-0.0.0.dist-info/top_level.txt
toyserve-0.0.0.dist-info/RECORD
