Metadata-Version: 2.4
Name: toyserve
Version: 0.0.0
Summary: toyserve
Requires-Python: >=3.11
